banner.py
gui.py
tasmotizer.py
tasmotizer_esptool.py
utils.py
tasmotizer-1.2.1.data/scripts/tasmotizer.py
tasmotizer-1.2.1.dist-info/METADATA
tasmotizer-1.2.1.dist-info/WHEEL
tasmotizer-1.2.1.dist-info/top_level.txt
tasmotizer-1.2.1.dist-info/RECORD
